<?xml version="1.0" encoding="UTF-8"?>
               <preferences version="10.0">
               
  <category name="Active Workspace Viewer">
    <category_description>Active Workspace Viewer-specific preferences.</category_description>
    
               <preference name="AWV0HostAWInVisUponLaunch" type="Logical" array="false" disabled="false" protectionScope="User" envEnabled="false">
      <preference_description>Determines if Active Workspace page is to be hosted inside Teamcenter Visualization when user launches part or product from Active Workspace.
When set to true, the Teamcenter Visualization starts showing Active Workspace page with part or product upon launch.</preference_description>
      <context name="Teamcenter">
        <value>false</value>
      </context>
    </preference>
    
               </category>
               </preferences>
               