<?xml version="1.0" encoding="UTF-8"?>
               <preferences version="10.0">
               
  <category name="Integration.CATIA">
    <category_description>No description available for this category.</category_description>
    
               <preference name="CATIA_loader_3Dviewer_datasettypes" type="String" array="true" disabled="false" protectionScope="User" envEnabled="false">
      <preference_description>Defines the dataset types list to display in the 3D viewer.</preference_description>
      <context name="Teamcenter">
        <value>DirectModel</value>
        <value>DirectModel3DMarkup</value>
        <value>Vis_Session</value>
      </context>
    </preference>
    
               </category>
               </preferences>
               