<?xml version="1.0" encoding="UTF-8"?>
               <preferences version="10.0">
               
  <category name="Substance Compliance">
    <category_description>Teamcenter Preferences for Substance Compliance</category_description>
    
               <preference name="ItemRevision_Scp0SubstanceCmplResult_default_relation" type="String" array="false" disabled="false" protectionScope="Site" envEnabled="false">
      <preference_description>Defines the default paste relation for ItemRevision object with Substance Compliance Result.</preference_description>
      <context name="Teamcenter">
      </context>
    </preference>
    
               </category>
               </preferences>
               