<?xml version="1.0" encoding="UTF-8"?>
               <preferences version="10.0">
               
  <category name="Manufacturing">
    <category_description>No description available for this category.</category_description>
    
               <preference name="MEAccountabilityCheckIncludedActivityProperties" type="String" array="true" disabled="false" protectionScope="Site" envEnabled="false">
      <preference_description>Defines the default list of properties to be included when comparing equivalent activities for partial match when using the accountability check.
Valid Values:
Accepts an array of strings representing the activity property names.</preference_description>
      <context name="Teamcenter">
        <value>al_activity_object_name</value>
        <value>al_activity_object_desc</value>
        <value>al_activity_current_name</value>
        <value>al_activity_current_desc</value>
        <value>al_activity_object_string</value>
        <value>al_activity_long_description</value>
        <value>al_activity_time_system_code</value>
        <value>al_activity_time_system_category</value>
        <value>al_activity_time_system_frequency</value>
        <value>al_activity_time_system_unit_time</value>
        <value>al_activity_time</value>
        <value>al_activity_calc_time</value>
        <value>al_activity_duration_time</value>
        <value>al_activity_work_time</value>
        <value>al_activity_start_time</value>
        <value>al_activity_calc_start_time</value>
        <value>me_cl_object_name</value>
        <value>me_cl_object_desc</value>
        <value>me_cl_current_name</value>
        <value>me_cl_current_desc</value>
        <value>me_cl_display_string</value>
      </context>
    </preference>
    
               </category>
               </preferences>
               