<?xml version="1.0" encoding="UTF-8"?>
               <preferences version="10.0">
               
  <category name="Product Structure.QSearch Configuration">
    <category_description>No description available for this category.</category_description>
    
               <preference name="QSEARCH_update_enabled" type="Logical" array="false" disabled="false" protectionScope="User" envEnabled="true">
      <preference_description>Enables or disables the automatic updating of indexes used by the cacheless spatial search mechanism.This preference can be set using the preference name as an environment variable.
Valid Values:
true - Enables automatic updates of spatial search indexes. The spatial index box data needed for spatial searches is generated for modified parts.
false - Disables automatic updates of spatial search indexes. Spatial index box data is not generated when parts are modified; spatial searches are unavailable due to lack of spatial data.</preference_description>
      <context name="Teamcenter">
        <value>false</value>
      </context>
    </preference>
    
               </category>
               </preferences>
               