<?xml version="1.0" encoding="UTF-8"?>
               <preferences version="10.0">
               
  <category name="Global Services.Options">
    <category_description>No description available for this category.</category_description>
    
               <preference name="TC_gms_gs_login_service_securi" type="String" array="false" disabled="false" protectionScope="Site" envEnabled="false">
      <preference_description>Locates the Global Services credential URI.</preference_description>
      <context name="Teamcenter">
        <value>http://teamcenter.com/globalservices/security/2006-12</value>
      </context>
    </preference>
    
               </category>
               </preferences>
               