<?xml version="1.0" encoding="UTF-8"?>
<preferences version="10.0">

  <category name="General">
    <category_description>No description available for this category.</category_description>

    <preference name="Vf6_MCNRevision_PseudoFolder" type="String" array="true" disabled="false"
      protectionScope="Site" envEnabled="false">
      <preference_description>This is an internal preference.</preference_description>
      <context name="Teamcenter">
        <value>C3D_View</value>
        <value>CAEAnalysis</value>
        <value>CMReferences</value>
        <value>Sci0IMDSView</value>
        <value>CMHasImpactedItem</value>
        <value>Vf6_impacted_shop</value>
        <value>CMImplementedBy</value>
        <value>CMImplements</value>
        <value>MEProcess</value>
        <value>MESetup</value>
        <value>PR4D_cad</value>
        <value>CMHasProblemItem</value>
        <value>Cm0HasProposal</value>
        <value>EC_solution_item_rel</value>
        <value>CMHasSolutionItem</value>
        <value>view</value>
        <value>catia</value>
        <value>catia_multi_model</value>
        <value>IMAN_specification</value>
      </context>
    </preference>

  </category>
</preferences>
               