<?xml version="1.0" encoding="UTF-8"?>
               <preferences version="10.0">
               
  <category name="General">
    <category_description>No description available for this category.</category_description>
    
               <preference name="VIS_multi_file_datasettypes" type="String" array="true" disabled="false" protectionScope="Site" envEnabled="false">
      <preference_description>Lists the Datasettypes that can contain more than one visualizable named references. This allows users to view the selected named reference in the My Navigator Viewer tab.</preference_description>
      <context name="Teamcenter">
        <value>DirectModel</value>
        <value>DrawingSheet</value>
      </context>
    </preference>
    
               </category>
               </preferences>
               